pjrpc/__init__.py
pjrpc/client/__init__.py
pjrpc/client/backend/__init__.py
pjrpc/client/backend/aio_pika.py
pjrpc/client/backend/aiohttp.py
pjrpc/client/backend/httpx.py
pjrpc/client/backend/requests.py
pjrpc/client/client.py
pjrpc/client/exceptions.py
pjrpc/client/integrations/__init__.py
pjrpc/client/integrations/pytest.py
pjrpc/client/integrations/pytest_aiohttp.py
pjrpc/client/integrations/pytest_requests.py
pjrpc/client/retry.py
pjrpc/client/validators.py
pjrpc/common/__init__.py
pjrpc/common/common.py
pjrpc/common/encoder.py
pjrpc/common/exceptions.py
pjrpc/common/generators.py
pjrpc/common/request.py
pjrpc/common/response.py
pjrpc/common/typedefs.py
pjrpc/py.typed
pjrpc/server/__init__.py
pjrpc/server/dispatcher.py
pjrpc/server/exceptions.py
pjrpc/server/integration/__init__.py
pjrpc/server/integration/aio_pika.py
pjrpc/server/integration/aiohttp.py
pjrpc/server/integration/flask.py
pjrpc/server/integration/werkzeug.py
pjrpc/server/specs/__init__.py
pjrpc/server/specs/extractors/__init__.py
pjrpc/server/specs/extractors/pydantic.py
pjrpc/server/specs/extractors/pydantic_v1.py
pjrpc/server/specs/openapi/__init__.py
pjrpc/server/specs/openapi/spec.py
pjrpc/server/specs/openapi/ui.py
pjrpc/server/specs/openrpc/__init__.py
pjrpc/server/specs/openrpc/spec.py
pjrpc/server/specs/schemas.py
pjrpc/server/typedefs.py
pjrpc/server/utils.py
pjrpc/server/validators/__init__.py
pjrpc/server/validators/base.py
pjrpc/server/validators/pydantic.py
pjrpc/server/validators/pydantic_v1.py
pjrpc-2.1.2.dist-info/METADATA
pjrpc-2.1.2.dist-info/WHEEL
pjrpc-2.1.2.dist-info/licenses/LICENSE
pjrpc-2.1.2.dist-info/RECORD
