Metadata-Version: 2.4
Name: pjrpc
Version: 2.1.2
Summary: Extensible JSON-RPC library
License: Unlicense
License-File: LICENSE
Keywords: json-rpc,jsonrpc-client,jsonrpc-server,openapi,openrpc
Author: Dmitry Pershin
Author-email: dapper1291@gmail.com
Requires-Python: >=3.9,<4.0
Classifier: Development Status :: 5 - Production/Stable
Classifier: Framework :: AsyncIO
Classifier: Framework :: Flask
Classifier: Framework :: Pytest
Classifier: Intended Audience :: Developers
Classifier: License :: OSI Approved
Classifier: License :: Public Domain
Classifier: Natural Language :: English
Classifier: Programming Language :: Python
Classifier: Programming Language :: Python :: 3
Classifier: Programming Language :: Python :: 3.9
Classifier: Programming Language :: Python :: 3.10
Classifier: Programming Language :: Python :: 3.11
Classifier: Programming Language :: Python :: 3.12
Classifier: Programming Language :: Python :: 3.13
Classifier: Programming Language :: Python :: 3.14
Classifier: Topic :: Internet :: WWW/HTTP
Classifier: Topic :: Software Development :: Libraries
Classifier: Topic :: Software Development :: Libraries :: Application Frameworks
Classifier: Typing :: Typed
Provides-Extra: aio-pika
Provides-Extra: aiohttp
Provides-Extra: flask
Provides-Extra: httpx
Provides-Extra: openapi-ui-bundles
Provides-Extra: pydantic
Provides-Extra: requests
Provides-Extra: werkzeug
Requires-Dist: aio-pika (>=8.0) ; extra == "aio-pika"
Requires-Dist: aiohttp (>=3.7) ; extra == "aiohttp"
Requires-Dist: flask (>=2.0.0) ; extra == "flask"
Requires-Dist: httpx (>=0.23.0) ; extra == "httpx"
Requires-Dist: openapi-ui-bundles (>=0.1) ; extra == "openapi-ui-bundles"
Requires-Dist: pydantic (>=1.10.20) ; extra == "pydantic"
Requires-Dist: requests (>=2.0) ; extra == "requests"
Requires-Dist: werkzeug (>=2.0) ; extra == "werkzeug"
Project-URL: Documentation, https://pjrpc.readthedocs.io
Project-URL: Homepage, https://github.com/dapper91/pjrpc
Project-URL: Repository, https://github.com/dapper91/pjrpc
